{
  "color-primary-100": "#DAF4FC",
  "color-primary-200": "#B6E7F9",
  "color-primary-300": "#8FCFEF",
  "color-primary-400": "#6FB4DF",
  "color-primary-500": "#438FCB",
  "color-primary-600": "#3070AE",
  "color-primary-700": "#215492",
  "color-primary-800": "#153B75",
  "color-primary-900": "#0C2961",
  "color-primary-transparent-100": "rgba(67, 143, 203, 0.08)",
  "color-primary-transparent-200": "rgba(67, 143, 203, 0.16)",
  "color-primary-transparent-300": "rgba(67, 143, 203, 0.24)",
  "color-primary-transparent-400": "rgba(67, 143, 203, 0.32)",
  "color-primary-transparent-500": "rgba(67, 143, 203, 0.4)",
  "color-primary-transparent-600": "rgba(67, 143, 203, 0.48)",
  "color-success-100": "#D3FDD2",
  "color-success-200": "#A6FBAC",
  "color-success-300": "#78F38D",
  "color-success-400": "#55E77C",
  "color-success-500": "#22D865",
  "color-success-600": "#18B964",
  "color-success-700": "#119B5F",
  "color-success-800": "#0A7D56",
  "color-success-900": "#066750",
  "color-success-transparent-100": "rgba(34, 216, 101, 0.08)",
  "color-success-transparent-200": "rgba(34, 216, 101, 0.16)",
  "color-success-transparent-300": "rgba(34, 216, 101, 0.24)",
  "color-success-transparent-400": "rgba(34, 216, 101, 0.32)",
  "color-success-transparent-500": "rgba(34, 216, 101, 0.4)",
  "color-success-transparent-600": "rgba(34, 216, 101, 0.48)",
  "color-info-100": "#D9F7FF",
  "color-info-200": "#B3EAFF",
  "color-info-300": "#8DDAFF",
  "color-info-400": "#71C9FF",
  "color-info-500": "#42ADFF",
  "color-info-600": "#3087DB",
  "color-info-700": "#2165B7",
  "color-info-800": "#154793",
  "color-info-900": "#0C327A",
  "color-info-transparent-100": "rgba(66, 173, 255, 0.08)",
  "color-info-transparent-200": "rgba(66, 173, 255, 0.16)",
  "color-info-transparent-300": "rgba(66, 173, 255, 0.24)",
  "color-info-transparent-400": "rgba(66, 173, 255, 0.32)",
  "color-info-transparent-500": "rgba(66, 173, 255, 0.4)",
  "color-info-transparent-600": "rgba(66, 173, 255, 0.48)",
  "color-warning-100": "#FFF4D6",
  "color-warning-200": "#FFE6AD",
  "color-warning-300": "#FFD483",
  "color-warning-400": "#FFC365",
  "color-warning-500": "#FFA632",
  "color-warning-600": "#DB8324",
  "color-warning-700": "#B76419",
  "color-warning-800": "#93490F",
  "color-warning-900": "#7A3509",
  "color-warning-transparent-100": "rgba(255, 166, 50, 0.08)",
  "color-warning-transparent-200": "rgba(255, 166, 50, 0.16)",
  "color-warning-transparent-300": "rgba(255, 166, 50, 0.24)",
  "color-warning-transparent-400": "rgba(255, 166, 50, 0.32)",
  "color-warning-transparent-500": "rgba(255, 166, 50, 0.4)",
  "color-warning-transparent-600": "rgba(255, 166, 50, 0.48)",
  "color-danger-100": "#FFE6DB",
  "color-danger-200": "#FFC6B7",
  "color-danger-300": "#FFA193",
  "color-danger-400": "#FF7D78",
  "color-danger-500": "#FF4C55",
  "color-danger-600": "#DB374E",
  "color-danger-700": "#B72647",
  "color-danger-800": "#93183F",
  "color-danger-900": "#7A0E3A",
  "color-danger-transparent-100": "rgba(255, 76, 85, 0.08)",
  "color-danger-transparent-200": "rgba(255, 76, 85, 0.16)",
  "color-danger-transparent-300": "rgba(255, 76, 85, 0.24)",
  "color-danger-transparent-400": "rgba(255, 76, 85, 0.32)",
  "color-danger-transparent-500": "rgba(255, 76, 85, 0.4)",
  "color-danger-transparent-600": "rgba(255, 76, 85, 0.48)"
}